similarity_ranker.py
similarity_ranker-1.0.3.dist-info/METADATA
similarity_ranker-1.0.3.dist-info/WHEEL
similarity_ranker-1.0.3.dist-info/entry_points.txt
similarity_ranker-1.0.3.dist-info/top_level.txt
similarity_ranker-1.0.3.dist-info/RECORD
