Metadata-Version: 2.1
Name: similarity-ranker
Version: 1.0.3
Requires-Dist: sentence-transformers
Requires-Dist: torch
Requires-Dist: scipy
